irida_sistr_results/CommandParseException.py
irida_sistr_results/SistrResultsException.py
irida_sistr_results/__init__.py
irida_sistr_results/irida_api.py
irida_sistr_results/irida_connector.py
irida_sistr_results/irida_sistr_results.py
irida_sistr_results/irida_sistr_workflow.py
irida_sistr_results/sistr_info.py
irida_sistr_results/sistr_writer.py
irida_sistr_results/version.py
irida_sistr_results/data/reportable_serovars.tsv
irida_sistr_results/etc/config.ini.example
irida_sistr_results-0.6.0.data/scripts/irida-sistr-results
irida_sistr_results-0.6.0.dist-info/METADATA
irida_sistr_results-0.6.0.dist-info/RECORD
irida_sistr_results-0.6.0.dist-info/WHEEL
irida_sistr_results-0.6.0.dist-info/top_level.txt
